configsimple/__init__.py
configsimple/configargparse.py
configsimple/configsimple.py
simpleconfig/__init__.py
simpleconfig/simpleconfig.py
configsimple-0.4.dist-info/LICENSE
configsimple-0.4.dist-info/METADATA
configsimple-0.4.dist-info/WHEEL
configsimple-0.4.dist-info/top_level.txt
configsimple-0.4.dist-info/RECORD
