Metadata-Version: 2.1
Name: configsimple
Version: 0.4
Summary: Configure components/classes using config files, command line options etc in a simple way
Home-page: http://github.com/johann-petrak/configsimple
Author: Johann Petrak
Author-email: johann.petrak@gmail.com
License: MIT
Platform: any
Classifier: License :: OSI Approved :: MIT License
Classifier: Natural Language :: English
Classifier: Programming Language :: Python :: 3
Classifier: Topic :: Software Development
Classifier: Intended Audience :: Developers
Requires-Python: >=3.5
